gtaxoprop.py
gtaxoprop-1.0.post3.dist-info/METADATA
gtaxoprop-1.0.post3.dist-info/WHEEL
gtaxoprop-1.0.post3.dist-info/entry_points.txt
gtaxoprop-1.0.post3.dist-info/top_level.txt
gtaxoprop-1.0.post3.dist-info/RECORD
