Metadata-Version: 2.4
Name: gtaxoprop
Version: 1.0.post3
Summary: A utility to generate input files for taxonomy propagation and assignment in QIIME/QIIME2 from the NCBI database
Home-page: https://gitlab.com/biomikalab/GTAXOPROP
Author: Maulana Malik Nashrulloh, Sonia Az Zahra Defi, Brian Rahardi, Muhammad Badrut Tamam, Riki Ruhimat, Hessy Novita
Author-email: maulana@genbinesia.or.id
License: GPLv3
Project-URL: Bug Reports, https://gitlab.com/biomikalab/GTAXOPROP/issues
Project-URL: Source, https://gitlab.com/biomikalab/GTAXOPROP
Project-URL: Documentation, https://gitlab.com/biomikalab/GTAXOPROP#readme
Keywords: bioinformatics,taxonomy,ncbi,qiime,qiime2,microbiome,microbiology,genomics
Classifier: Programming Language :: Python :: 3
Classifier: Programming Language :: Python :: 3.10
Classifier: Programming Language :: Python :: 3.11
Classifier: Programming Language :: Python :: 3.12
Classifier: Programming Language :: Python :: 3.13
Classifier: Programming Language :: Python :: 3.14
Classifier: License :: OSI Approved :: GNU General Public License v3 (GPLv3)
Classifier: Operating System :: OS Independent
Classifier: Topic :: Scientific/Engineering :: Bio-Informatics
Classifier: Intended Audience :: Science/Research
Classifier: Natural Language :: English
Classifier: Development Status :: 5 - Production/Stable
Requires-Python: >=3.10
Requires-Dist: tinydb==4.8.2
Requires-Dist: pbr>=6.1.1
Requires-Dist: stevedore>=5.5.0
Requires-Dist: cogent3>=2025.9.8a2
Requires-Dist: biopython>=1.85
Dynamic: author
Dynamic: author-email
Dynamic: classifier
Dynamic: description
Dynamic: description-content-type
Dynamic: home-page
Dynamic: keywords
Dynamic: license
Dynamic: project-url
Dynamic: requires-dist
Dynamic: requires-python
Dynamic: summary
